{
  "authentication": {
    "available_types": [{
      "name": "mock",
      "namespace": "erdiko_authenticate_Services",
      "classname": "Mock",
      "enabled": true
    }]
  },
  "storage": {
    "selected": "session",
    "storage_types": [{
      "name": "session",
      "namespace": "erdiko_authenticate_Services",
      "classname": "SessionStorage",
      "enabled": true
    }]
  },
  "guards":[
    "dashboard",
    "index"
  ],
  "policies": {
    "anonymous" : {
      "index":{
        "read":"allow",
        "login": "allow"
      },
      "dashboard":{
        "read":"allow"
      }
    }
  }
}